kagglesdk/__init__.py
kagglesdk/kaggle_client.py
kagglesdk/kaggle_creds.py
kagglesdk/kaggle_env.py
kagglesdk/kaggle_http_client.py
kagglesdk/kaggle_oauth.py
kagglesdk/kaggle_object.py
kagglesdk/admin/__init__.py
kagglesdk/admin/services/__init__.py
kagglesdk/admin/services/inbox_file_service.py
kagglesdk/admin/types/__init__.py
kagglesdk/admin/types/inbox_file_service.py
kagglesdk/benchmarks/__init__.py
kagglesdk/benchmarks/services/__init__.py
kagglesdk/benchmarks/services/benchmarks_api_service.py
kagglesdk/benchmarks/types/__init__.py
kagglesdk/benchmarks/types/benchmark_types.py
kagglesdk/benchmarks/types/benchmarks_api_service.py
kagglesdk/blobs/__init__.py
kagglesdk/blobs/services/__init__.py
kagglesdk/blobs/services/blob_api_service.py
kagglesdk/blobs/types/__init__.py
kagglesdk/blobs/types/blob_api_service.py
kagglesdk/common/__init__.py
kagglesdk/common/services/__init__.py
kagglesdk/common/services/operations_service.py
kagglesdk/common/types/__init__.py
kagglesdk/common/types/file_download.py
kagglesdk/common/types/http_redirect.py
kagglesdk/common/types/operations.py
kagglesdk/common/types/operations_service.py
kagglesdk/community/__init__.py
kagglesdk/community/types/__init__.py
kagglesdk/community/types/content_enums.py
kagglesdk/community/types/organization.py
kagglesdk/competitions/__init__.py
kagglesdk/competitions/services/__init__.py
kagglesdk/competitions/services/competition_api_service.py
kagglesdk/competitions/types/__init__.py
kagglesdk/competitions/types/competition.py
kagglesdk/competitions/types/competition_api_service.py
kagglesdk/competitions/types/competition_enums.py
kagglesdk/competitions/types/search_competitions.py
kagglesdk/competitions/types/submission_status.py
kagglesdk/datasets/__init__.py
kagglesdk/datasets/databundles/__init__.py
kagglesdk/datasets/databundles/types/__init__.py
kagglesdk/datasets/databundles/types/databundle_api_types.py
kagglesdk/datasets/services/__init__.py
kagglesdk-0.1.12.dist-info/METADATA
kagglesdk-0.1.12.dist-info/WHEEL
kagglesdk-0.1.12.dist-info/licenses/LICENSE
kagglesdk-0.1.12.dist-info/RECORD
