Metadata-Version: 2.4
Name: kagglesdk
Version: 0.1.12
Summary: Bindings to access kaggle's external-facing APIs
Project-URL: Homepage, https://github.com/Kaggle/kagglesdk
Project-URL: Bug Tracker, https://github.com/Kaggle/kagglesdk/issues
Author-email: Kaggle <support@kaggle.com>
License:                                  Apache License
License-File: LICENSE
Keywords: API,Kaggle
Classifier: License :: OSI Approved :: Apache Software License
Classifier: Operating System :: OS Independent
Classifier: Programming Language :: Python :: 3
Requires-Python: >=3.9
Requires-Dist: requests
